custom_fixers
sphinx
hgblog
