Metadata-Version: 1.0
Name: hgblog
Version: 0.7.1
Summary: Sphinx-based blogging engine
Home-page: http://bitbucket.org/codekoala/hgblog/
Author: Josh VanderLinden
Author-email: codekoala@gmail.com
License: BSD
Download-URL: http://pypi.python.org/pypi/hgblog
Platform: any
Classifier: Development Status :: 5 - Production/Stable
Classifier: Environment :: Console
Classifier: Environment :: Web Environment
Classifier: Intended Audience :: Developers
Classifier: Intended Audience :: Education
Classifier: License :: OSI Approved :: BSD License
Classifier: Operating System :: OS Independent
Classifier: Programming Language :: Python
Classifier: Programming Language :: Python :: 2
Classifier: Topic :: Documentation
Classifier: Topic :: Text Processing
Classifier: Topic :: Utilities
